paos/__init__.py
paos/classes/__init__.py
paos/classes/abcd.py
paos/classes/psd.py
paos/classes/wfo.py
paos/classes/zernike.py
paos/core/__init__.py
paos/core/coordinateBreak.py
paos/core/parseConfig.py
paos/core/pipeline.py
paos/core/plot.py
paos/core/raytrace.py
paos/core/retired/paos_parseconfig_temp.py
paos/core/run.py
paos/core/saveOutput.py
paos/gui/__init__.py
paos/gui/app.py
paos/gui/core/__init__.py
paos/gui/core/elems.py
paos/gui/core/io.py
paos/gui/core/plot.py
paos/gui/core/shared.py
paos/gui/gui.py
paos/gui/www/layout.css
paos/gui/www/static/logo.png
paos/log/__init__.py
paos/log/logger.py
paos/paos.py
paos/util/__init__.py
paos/util/lib.py
paos/util/material.py
paos-1.2.12.dist-info/METADATA
paos-1.2.12.dist-info/WHEEL
paos-1.2.12.dist-info/entry_points.txt
paos-1.2.12.dist-info/licenses/LICENSE
paos-1.2.12.dist-info/RECORD
