Metadata-Version: 2.4
Name: paos
Version: 1.2.12
Summary: PAOS, the Physical Optics Simulator, is a fast, modern, and reliable Python package for Physical Optics studies. It implements Physical Optics Propagation in Fresnel approximation and paraxial ray tracing to analyze complex waveform propagation through both generic and off-axes optical systems.
License: BSD-3-Clause
License-File: LICENSE
Keywords: python,open-source,psf,gui,optics,wavefront,ray-tracing,fresnel,optics-simulation,paos
Author: Andrea Bocchieri
Author-email: andrea.bocchieri@uniroma1.it
Requires-Python: >=3.9,<4.0
Classifier: Development Status :: 5 - Production/Stable
Classifier: Environment :: Console
Classifier: Intended Audience :: Developers
Classifier: Intended Audience :: Science/Research
Classifier: License :: OSI Approved :: BSD License
Classifier: Operating System :: OS Independent
Classifier: Programming Language :: Python :: 3
Classifier: Programming Language :: Python :: 3.9
Classifier: Programming Language :: Python :: 3.10
Classifier: Programming Language :: Python :: 3.11
Classifier: Programming Language :: Python :: 3.12
Classifier: Programming Language :: Python :: 3.13
Classifier: Programming Language :: Python :: 3.14
Classifier: Topic :: Scientific/Engineering
Classifier: Topic :: Software Development :: Libraries
Requires-Dist: decorator
Requires-Dist: faicons
Requires-Dist: h5py
Requires-Dist: ipykernel
Requires-Dist: jinja2
Requires-Dist: joblib
Requires-Dist: loguru
Requires-Dist: marimo
Requires-Dist: matplotlib
Requires-Dist: numpy
Requires-Dist: orjson
Requires-Dist: photutils
Requires-Dist: rich-click
Requires-Dist: scikit-image
Requires-Dist: scipy
Requires-Dist: shiny
Requires-Dist: shinywidgets
Requires-Dist: sympy
Requires-Dist: tqdm
Project-URL: Documentation, https://paos.readthedocs.io/en/latest/
Project-URL: Homepage, https://github.com/arielmission-space/PAOS
Project-URL: Repository, https://github.com/arielmission-space/PAOS.git
